mydependency/__init__.py
mydependency-0.0.0.dist-info/METADATA
mydependency-0.0.0.dist-info/WHEEL
mydependency-0.0.0.dist-info/top_level.txt
mydependency-0.0.0.dist-info/RECORD
