Metadata-Version: 2.1
Name: mydependency
Version: 0.0.0
Summary: Don't take my package name
Home-page: UNKNOWN
Author: Nicolas REMOND
Author-email: remondnicola@gmail.com
License: UNKNOWN
Platform: UNKNOWN
Classifier: Programming Language :: Python :: 3.7
Classifier: Operating System :: OS Independent
Requires-Python: >=3.7
Provides-Extra: all
Requires-Dist: pytest (~=7.0) ; extra == 'all'
Requires-Dist: pytest-cov (~=3.0) ; extra == 'all'
Requires-Dist: coverage-badge (~=1.0) ; extra == 'all'
Requires-Dist: pre-commit (~=2.15) ; extra == 'all'
Requires-Dist: isort (~=5.9) ; extra == 'all'
Requires-Dist: black (~=22.1) ; extra == 'all'
Requires-Dist: flake518 (~=1.2) ; extra == 'all'
Requires-Dist: darglint (~=1.8) ; extra == 'all'
Requires-Dist: mkdocs-material (~=8.1) ; extra == 'all'
Requires-Dist: mkdocstrings[python] (~=0.18) ; extra == 'all'
Requires-Dist: mike (~=1.1) ; extra == 'all'
Provides-Extra: dev
Requires-Dist: pytest (~=7.0) ; extra == 'dev'
Requires-Dist: pytest-cov (~=3.0) ; extra == 'dev'
Requires-Dist: coverage-badge (~=1.0) ; extra == 'dev'
Requires-Dist: pre-commit (~=2.15) ; extra == 'dev'
Requires-Dist: isort (~=5.9) ; extra == 'dev'
Requires-Dist: black (~=22.1) ; extra == 'dev'
Requires-Dist: flake518 (~=1.2) ; extra == 'dev'
Requires-Dist: darglint (~=1.8) ; extra == 'dev'
Requires-Dist: mkdocs-material (~=8.1) ; extra == 'dev'
Requires-Dist: mkdocstrings[python] (~=0.18) ; extra == 'dev'
Requires-Dist: mike (~=1.1) ; extra == 'dev'
Provides-Extra: docs
Requires-Dist: mkdocs-material (~=8.1) ; extra == 'docs'
Requires-Dist: mkdocstrings[python] (~=0.18) ; extra == 'docs'
Requires-Dist: mike (~=1.1) ; extra == 'docs'
Provides-Extra: hook
Requires-Dist: pre-commit (~=2.15) ; extra == 'hook'
Provides-Extra: lint
Requires-Dist: isort (~=5.9) ; extra == 'lint'
Requires-Dist: black (~=22.1) ; extra == 'lint'
Requires-Dist: flake518 (~=1.2) ; extra == 'lint'
Requires-Dist: darglint (~=1.8) ; extra == 'lint'
Provides-Extra: test
Requires-Dist: pytest (~=7.0) ; extra == 'test'
Requires-Dist: pytest-cov (~=3.0) ; extra == 'test'
Requires-Dist: coverage-badge (~=1.0) ; extra == 'test'
